pyworld/__init__.py
pyworld/pyworld.cp310-win_arm64.pyd
pyworld/pyworld.pyi
pyworld_prebuilt-0.3.5.post1.dist-info/licenses/LICENSE
pyworld_prebuilt-0.3.5.post1.dist-info/METADATA
pyworld_prebuilt-0.3.5.post1.dist-info/WHEEL
pyworld_prebuilt-0.3.5.post1.dist-info/top_level.txt
pyworld_prebuilt-0.3.5.post1.dist-info/RECORD
