Metadata-Version: 2.4
Name: pyworld-prebuilt
Version: 0.3.5.post1
Summary: PyWorld: a Python wrapper for WORLD vocoder
Home-page: https://github.com/tsukumijima/pyworld-prebuilt
Author: Pyworld Contributors
Author-email: jeremycchsu@gmail.com
Keywords: vocoder
License-File: LICENSE
Requires-Dist: numpy
Provides-Extra: test
Requires-Dist: nose; extra == "test"
Provides-Extra: sdist
Requires-Dist: numpy; extra == "sdist"
Requires-Dist: cython>=3.0; extra == "sdist"
Dynamic: author
Dynamic: author-email
Dynamic: description
Dynamic: description-content-type
Dynamic: home-page
Dynamic: keywords
Dynamic: license-file
Dynamic: provides-extra
Dynamic: requires-dist
Dynamic: summary
